Workbook
Name Revenue: tbl_actuals[Revenue]

Sheet Actuals
A1: Date | B1: Department | C1: Revenue | D1: Total Cost | E1: Profit | F1: Utilization Rate
A2: 44957 | B2: Digital Transformation | C2: 16888.91 | D2: 11720.22 | E2: 5168.69 | F2: 0.774
A3: 44985 | B3: Digital Transformation | C3: 19441.45 | D3: 14948.93 | E3: 4492.52 | F3: 0.842
A4: 45016 | B4: Digital Transformation | C4: 16711.45 | D4: 12164.62 | E4: 4546.83 | F4: 0.727
A5: 45046 | B5: Digital Transformation | C5: 16346.3 | D5: 12374.01 | E5: 3972.29 | F5: 0.773
A6: 45077 | B6: Digital Transformation | C6: 20158.54 | D6: 13502.77 | E6: 6655.77 | F6: 0.883
A7: 45107 | B7: Digital Transformation | C7: 19480.48 | D7: 12666.32 | E7: 6814.16 | F7: 0.868
A8: 45138 | B8: Digital Transformation | C8: 16499.35 | D8: 11959.52 | E8: 4539.83 | F8: 0.721
A9: 45169 | B9: Digital Transformation | C9: 15457.38 | D9: 11903.82 | E9: 3553.56 | F9: 0.678
A10: 45199 | B10: Digital Transformation | C10: 17569.49 | D10: 12349.36 | E10: 5220.13 | F10: 0.799
A11: 45230 | B11: Digital Transformation | C11: 16487.1 | D11: 11138.08 | E11: 5349.02 | F11: 0.778
A12: 45260 | B12: Digital Transformation | C12: 17377.43 | D12: 11309.45 | E12: 6067.98 | F12: 0.777
A13: 45291 | B13: Digital Transformation | C13: 17622.47 | D13: 11615.81 | E13: 6006.66 | F13: 0.828
... A73: 45657 | B73: Infrastructure Advisory | C73: 14847.18 | D73: 11380.97 | E73: 3466.21 | F73: 0.756

Sheet Assumptions
A1: Scenario | B1: Conservative
A4: Parameter | B4: Base | C4: Optimistic | D4: Conservative
A5: Avg Daily Rate | B5: 1000 | C5: 1050 | D5: 950
A6: Utilization % | B6: 0.78 | C6: 0.82 | D6: 0.72
A7: Cost Inflation % | B7: 0.03 | C7: 0.02 | D7: 0.05
A8: Selected Avg Daily Rate | B8: {=_xlfn.XLOOKUP($B$1, Table2[[#Headers],[Base]:[Conservative]],$B$5:$D$5)} -> 950
A9: Selected Utilization | B9: {=_xlfn.XLOOKUP($B$1, Table2[[#Headers],[Base]:[Conservative]],$B$6:$D$6)} -> 0.72
A10: Selected Cost Inflation | B10: {=_xlfn.XLOOKUP($B$1,Table2[[#Headers],[Base]:[Conservative]],$B$7:$D$7)} -> 0.05
A12: I used a scenario selector with Xlookup to dynamically switch forecast assumptions without changing formulas

Sheet Forecast
A4: Month | B4: Available Days | C4: Forecast Revenue | D4: Forecast Cost | E4: Forecast Profit
A5: 45688 | B5: 20 | C5: =B5*Assumptions!$B$9*Assumptions!$B$8 -> 13680 | D5: {=LOOKUP(2,1/(Actuals!$A:$A<>""),Actuals!$D:$D) * (1 + Assumptions!$B$10)} -> 11950.019 | E5: =C5-D5 -> 1729.9815
A6: 45716 | B6: 20 | C6: =B6*Assumptions!$B$9*Assumptions!$B$8 -> 13680 | D6: =D5 * (1 + Assumptions!$B$10) -> 12547.519 | E6: =C6-D6 -> 1132.4806
A7: 45747 | B7: 20 | C7: =B7*Assumptions!$B$9*Assumptions!$B$8 -> 13680 | D7: =D6 * (1 + Assumptions!$B$10) -> 13174.895 | E7: =C7-D7 -> 505.1046
A8: 45777 | B8: 20 | C8: =B8*Assumptions!$B$9*Assumptions!$B$8 -> 13680 | D8: =D7 * (1 + Assumptions!$B$10) -> 13833.64 | E8: =C8-D8 -> -153.64017
A9: 45808 | B9: 20 | C9: =B9*Assumptions!$B$9*Assumptions!$B$8 -> 13680 | D9: =D8 * (1 + Assumptions!$B$10) -> 14525.322 | E9: =C9-D9 -> -845.32217
A10: 45838 | B10: 20 | C10: =B10*Assumptions!$B$9*Assumptions!$B$8 -> 13680 | D10: =D9 * (1 + Assumptions!$B$10) -> 15251.588 | E10: =C10-D10 -> -1571.5883
A12: Make Cost Roll Forward Month by Month
A13: First forecast month = last actual cost x (1+inflation)
A14: Next forecast month = previous forecast cost x (1+inflation)
A16: Forecast Cost = Last Actual cost x (1 + Cost Inflation)
A17: I built a driver-based forecast in Excel where utilization, daily rates, and inflation assumptions dynamically drive future revenue and profit

Sheet Variance Analysis 
A4: Metric | B4: Actual | C4: Forecast | D4: Variance | E4: Variance %
A5: Revenue | B5: {=LOOKUP(2,1/(Actuals!$A:$A<>""),Actuals!$C:$C)} -> 14847.18 | C5: =Table4[[#This Row],[Forecast Revenue]] -> 13680 | D5: =Table5[[#This Row],[Forecast]]-Table5[[#This Row],[Actual]] -> -1167.18 | E5: =IF(B5=0,"",(C5-B5)/B5) -> -0.078612908
A6: Profit | B6: {=LOOKUP(2,1/(Actuals!$A:$A<>""),Actuals!$E:$E)} -> 3466.21 | C6: =Forecast!E5 -> 1729.9815 | D6: =Table5[[#This Row],[Forecast]]-Table5[[#This Row],[Actual]] -> -1736.2285 | E6: =IF(B6=0,"",(C6-B6)/B6) -> -0.50090113
A9: I dynamically pulled the most recent actuals and compared them to the next forecast period to highlight short-term performance gaps
A11: Variance mainly driven by utilization assumptions and daily rate changes under selected scenario
A13: I compared the latest actuals with the next forecast period and calculated absolute and relative variances to highlight short-term performance gaps and their drivers

Sheet Management KPI
A3: KPI | B3: Actual (Latest) | C3: Forecast (Next Period)
A4: Revenue | B4: {=LOOKUP(2,1/(Actuals!$A:$A<>""),Actuals!$C:$C)} -> 14847.18 | C4: =Forecast!C5 -> 13680
A5: Profit (EBIT) | B5: {=LOOKUP(2,1/(Actuals!$A:$A<>""),Actuals!$E:$E)} -> 3466.21 | C5: =Table4[[#This Row],[Forecast Profit]] -> 1729.9815
A6: EBIT Margin | B6: =B5/B4 -> 0.23345915 | C6: =C5/C4 -> 0.12646064
A7: Utilization | B7: {=LOOKUP(2,1/(Actuals!$A:$A<>""),Actuals!$F:$F)} -> 0.756 | C7: =Assumptions!$B$9 -> 0.72
A8: Revenue per Day | B8: =B5 / (20 * B7) -> 229.24669 | C8: =C4/(20*C7) -> 950
A10: I created a management KPI sheet that consolidates actuals and forecast into decision-oriented metrics, designed as a handoff to executive reporting
